pymapping/__about__.py
pymapping/__init__.py
pymapping/__main__.py
pymapping/cli.py
pymapping/main.py
pymapping-0.1.1.dist-info/LICENSE
pymapping-0.1.1.dist-info/METADATA
pymapping-0.1.1.dist-info/WHEEL
pymapping-0.1.1.dist-info/entry_points.txt
pymapping-0.1.1.dist-info/top_level.txt
pymapping-0.1.1.dist-info/RECORD
