Metadata-Version: 2.1
Name: pymapping
Version: 0.1.1
Summary: Mapping finite element data between meshes
Home-page: https://github.com/tianyikillua/pymapping
Author: Tianyi Li
Author-email: tianyikillua@gmail.com
License: License :: OSI Approved :: MIT License
Platform: UNKNOWN
Classifier: License :: OSI Approved :: MIT License
Classifier: Development Status :: 4 - Beta
Classifier: Operating System :: Microsoft :: Windows
Classifier: Operating System :: Unix
Classifier: Programming Language :: Python
Classifier: Programming Language :: Python :: 3.6
Classifier: Programming Language :: Python :: 3.7
Classifier: Intended Audience :: Science/Research
Classifier: Topic :: Scientific/Engineering
Classifier: Topic :: Scientific/Engineering :: Physics
Requires-Dist: numpy
Requires-Dist: meshio
Requires-Dist: medcoupling
